djadmin.py
setup.py
djadmin_template.egg-info/PKG-INFO
djadmin_template.egg-info/SOURCES.txt
djadmin_template.egg-info/dependency_links.txt
djadmin_template.egg-info/entry_points.txt
djadmin_template.egg-info/top_level.txt