Metadata-Version: 1.0
Name: djadmin-template
Version: 0.1.0
Summary: Wrapped django-admin tool for modify project and app template to add encoding, author, date and so on
Home-page: https://github.com/MythRen/wrapped-django-admin
Author: Myth
Author-email: email4myth@gmail.com
License: None
Platform: UNKNOWN
